README.md
setup.cfg
setup.py
MySQLWrapperPackage/__init__.py
MySQLWrapperPackage/connections.py
MySQLWrapperPackage/mysqlquerries.py
MySQLWrapperPackage/wrapper.py
MySQLWrapperPackage/wrapperabstraction.py
mysqlwrapperpackage1.egg-info/PKG-INFO
mysqlwrapperpackage1.egg-info/SOURCES.txt
mysqlwrapperpackage1.egg-info/dependency_links.txt
mysqlwrapperpackage1.egg-info/not-zip-safe
mysqlwrapperpackage1.egg-info/requires.txt
mysqlwrapperpackage1.egg-info/top_level.txt