Metadata-Version: 1.1
Name: mysqlwrapperpackage1
Version: 1.2
Summary: MySQL Python Wrapper Package
Home-page: https://github.com/Sharonsyra
Author: Sharon Waithira
Author-email: sharonwaithii@gmail.com
License: MIT
Download-URL: https://github.com/Sharonsyra/MySQLWrapperPackage/archive/v1.2.tar.gz
Platform: UNKNOWN
